lavague/sdk/__init__.py
lavague/sdk/action/__init__.py
lavague/sdk/action/base.py
lavague/sdk/action/extraction.py
lavague/sdk/action/navigation.py
lavague/sdk/agent.py
lavague/sdk/base_driver/__init__.py
lavague/sdk/base_driver/base.py
lavague/sdk/base_driver/interaction.py
lavague/sdk/base_driver/javascript.py
lavague/sdk/base_driver/node.py
lavague/sdk/base_exporter.py
lavague/sdk/cli.py
lavague/sdk/client.py
lavague/sdk/exceptions.py
lavague/sdk/trajectory/__init__.py
lavague/sdk/trajectory/base.py
lavague/sdk/trajectory/controller.py
lavague/sdk/trajectory/mock.py
lavague/sdk/trajectory/model.py
lavague/sdk/utilities/config.py
lavague/sdk/utilities/format_utils.py
lavague/sdk/utilities/version_checker.py
lavague_sdk-0.1.0.dist-info/LICENSE
lavague_sdk-0.1.0.dist-info/METADATA
lavague_sdk-0.1.0.dist-info/WHEEL
lavague_sdk-0.1.0.dist-info/RECORD
